README.md
setup.cfg
setup.py
neo4japi/__init__.py
neo4japi/api.py
neo4japi/cql.py
neo4japi/parser.py
neo4japi.egg-info/PKG-INFO
neo4japi.egg-info/SOURCES.txt
neo4japi.egg-info/dependency_links.txt
neo4japi.egg-info/not-zip-safe
neo4japi.egg-info/requires.txt
neo4japi.egg-info/top_level.txt
test/test_api.py