Metadata-Version: 2.1
Name: neo4japi
Version: 1.1.2
Summary: A simple neo4j api driver
Home-page: https://github.com/floatliang/neo4japi
Author: floatsliang
Author-email: utavianus@qq.com
License: UNKNOWN
Keywords: neo4j driver api
Platform: any
Classifier: Development Status :: 4 - Beta
Classifier: Intended Audience :: Developers
Classifier: Topic :: Software Development :: Libraries :: Python Modules
Classifier: License :: OSI Approved :: MIT License
Classifier: Operating System :: OS Independent
Classifier: Programming Language :: Python :: 3
Classifier: Programming Language :: Python :: 3.4
Classifier: Programming Language :: Python :: 3.5
Classifier: Programming Language :: Python :: 3.6
Classifier: Programming Language :: Python :: 3.7
